abstract_producer/__init__.py
abstract_producer/_version.py
abstract_producer/abstraction.py
abstract_producer/api.py
abstract_producer/buffer.py
abstract_producer/consumer.py
abstract_producer/exc.py
abstract_producer/logger.py
abstract_producer/paths.py
abstract_producer/producer.py
abstract_producer/record.py
abstract_producer/utils.py
abstract_producer/buffers/__init__.py
abstract_producer/buffers/file_buffer.py
abstract_producer/consumers/__init__.py
abstract_producer/consumers/aws_kinesis.py
abstract_producer/consumers/simple.py
abstract_producer/docs/__init__.py
abstract_producer/producers/__init__.py
abstract_producer/producers/aws_cloudwatch_logs.py
abstract_producer/producers/aws_kinesis.py
abstract_producer/producers/simple.py
abstract_producer/records/__init__.py
abstract_producer/records/aws_kinesis.py
abstract_producer/records/dataclass.py
abstract_producer/tests/__init__.py
abstract_producer/tests/helper.py
abstract_producer/tests/mock_aws.py
abstract_producer/vendor/__init__.py
abstract_producer/vendor/aws_cloudwatch_logs_insights_query.py
abstract_producer/vendor/better_dataclass.py
abstract_producer/vendor/better_enum.py
abstract_producer/vendor/nested_logger.py
abstract_producer/vendor/pytest_cov_helper.py
abstract_producer-0.3.1.dist-info/AUTHORS.rst
abstract_producer-0.3.1.dist-info/LICENSE.txt
abstract_producer-0.3.1.dist-info/METADATA
abstract_producer-0.3.1.dist-info/WHEEL
abstract_producer-0.3.1.dist-info/top_level.txt
abstract_producer-0.3.1.dist-info/RECORD
